slurm_parallel/__init__.py
slurm_parallel/config.toml
slurm_parallel/run.py
slurm_parallel/run.sh
slurm_parallel/slurm.py
slurm_parallel/summarize.sh
slurm_parallel/utils.py
slurm_parallel-0.1.7.dist-info/LICENSE
slurm_parallel-0.1.7.dist-info/METADATA
slurm_parallel-0.1.7.dist-info/WHEEL
slurm_parallel-0.1.7.dist-info/top_level.txt
slurm_parallel-0.1.7.dist-info/RECORD
