Metadata-Version: 2.1
Name: slurm-parallel
Version: 0.1.7
Summary: Easy parallelization of python functions on SLURM using job arrays.
Author: Ho Yin Chau
License: MIT License
Project-URL: repository, https://github.com/hchau630/slurm-parallel
Classifier: License :: OSI Approved :: MIT License
Classifier: Natural Language :: English
Classifier: Operating System :: OS Independent
Classifier: Programming Language :: Python :: 3.9
Requires-Python: >=3.9
License-File: LICENSE
Requires-Dist: hyclib (>=0.1.14)
Requires-Dist: tqdm
